_package.py
bootstrap.py
run.py
api/__init__.py
api/dependencies.py
api/py.typed
api/server.py
api/validation.py
api/documentation/__init__.py
api/documentation/examples.py
api/documentation/openapi_config.py
api/documentation/py.typed
api/documentation/security_schemes.py
api/handlers/__init__.py
api/handlers/get_available_templates_handler.py
api/handlers/get_request_status_handler.py
api/handlers/get_return_requests_handler.py
api/handlers/py.typed
api/handlers/request_machines_handler.py
api/handlers/request_return_machines_handler.py
api/middleware/__init__.py
api/middleware/auth_middleware.py
api/middleware/logging_middleware.py
api/middleware/py.typed
api/models/__init__.py
api/models/base.py
api/models/py.typed
api/models/request_machines.py
api/models/requests.py
api/models/responses.py
api/models/templates.py
api/routers/__init__.py
api/routers/machines.py
api/routers/py.typed
api/routers/requests.py
api/routers/templates.py
application/__init__.py
application/decorators.py
application/py.typed
application/base/__init__.py
application/base/command_handler.py
application/base/commands.py
application/base/event_handlers.py
application/base/handlers.py
application/base/infrastructure_handlers.py
application/base/provider_handlers.py
application/base/py.typed
application/base/queries.py
application/commands/__init__.py
application/commands/cleanup_handlers.py
application/commands/machine_handlers.py
application/commands/provider_handlers.py
application/commands/py.typed
application/commands/request_handlers.py
application/commands/system.py
application/commands/system_handlers.py
application/commands/template_handlers.py
application/dto/__init__.py
application/dto/base.py
application/dto/commands.py
application/dto/py.typed
application/dto/queries.py
application/dto/responses.py
application/dto/system.py
application/events/__init__.py
application/events/decorators.py
application/events/py.typed
application/events/base/__init__.py
open_hostfactory_plugin-0.1.0.dist-info/licenses/LICENSE
open_hostfactory_plugin-0.1.0.dist-info/METADATA
open_hostfactory_plugin-0.1.0.dist-info/WHEEL
open_hostfactory_plugin-0.1.0.dist-info/entry_points.txt
open_hostfactory_plugin-0.1.0.dist-info/top_level.txt
open_hostfactory_plugin-0.1.0.dist-info/RECORD
