Metadata-Version: 2.4
Name: open-hostfactory-plugin
Version: 0.1.0
Summary: Cloud provider integration plugin for IBM Spectrum Symphony Host Factory
Author-email: AWS Professional Services <aws-proserve@amazon.com>
Maintainer-email: AWS Professional Services <aws-proserve@amazon.com>
License-Expression: Apache-2.0
Project-URL: Homepage, https://github.com/awslabs/open-hostfactory-plugin
Project-URL: Documentation, https://awslabs.github.io/open-hostfactory-plugin/
Project-URL: Repository, https://github.com/awslabs/open-hostfactory-plugin
Project-URL: Bug Reports, https://github.com/awslabs/open-hostfactory-plugin/issues
Keywords: aws,ec2,hostfactory,symphony,hpc,cluster,cloud,infrastructure
Classifier: Development Status :: 4 - Beta
Classifier: Intended Audience :: Developers
Classifier: Natural Language :: English
Classifier: Operating System :: OS Independent
Classifier: Programming Language :: Python :: 3
Classifier: Programming Language :: Python :: 3.9
Classifier: Programming Language :: Python :: 3.10
Classifier: Programming Language :: Python :: 3.11
Classifier: Programming Language :: Python :: 3.12
Classifier: Programming Language :: Python :: 3.13
Classifier: Topic :: Software Development :: Libraries :: Python Modules
Classifier: Topic :: System :: Clustering
Classifier: Topic :: System :: Distributed Computing
Requires-Python: >=3.9
License-File: LICENSE
Requires-Dist: boto3>=1.26.0
Requires-Dist: botocore>=1.29.0
Requires-Dist: pydantic>=2.0.0
Requires-Dist: sqlalchemy>=2.0.0
Requires-Dist: dynaconf>=3.2.0
Requires-Dist: structlog>=23.1.0
Requires-Dist: opentelemetry-api>=1.20.0
Requires-Dist: opentelemetry-sdk>=1.20.0
Requires-Dist: psutil>=5.9.0
Requires-Dist: prometheus-client>=0.17.0
Requires-Dist: jsonschema>=4.17.0
Requires-Dist: rich>=13.3.0
Requires-Dist: python-dotenv>=1.0.0
Requires-Dist: PyJWT>=2.8.0
Requires-Dist: cryptography>=41.0.0
Requires-Dist: requests>=2.31.0
Requires-Dist: PyYAML>=6.0.0
Requires-Dist: click>=8.0.0
Requires-Dist: fastapi>=0.104.0
Requires-Dist: uvicorn>=0.24.0
Requires-Dist: jinja2>=3.1.0
Dynamic: license-file
